{
  "updated_at": "2026-06-29T12:00:00Z",
  "tournament": "FIFA World Cup 2026",
  "note": "小组赛已于 6/27 结束，现进入 32 强阶段",
  "groups": {
    "A": [
      {"team": "Mexico", "position": 1, "points": 9, "played": 3, "won": 3, "draw": 0, "lost": 0, "goal_difference": 5, "goals_for": 6, "goals_against": 1},
      {"team": "South Africa", "position": 2, "points": 3, "played": 3, "won": 1, "draw": 0, "lost": 2, "goal_difference": -2, "goals_for": 1, "goals_against": 3},
      {"team": "South Korea", "position": 3, "points": 3, "played": 3, "won": 1, "draw": 0, "lost": 2, "goal_difference": 0, "goals_for": 3, "goals_against": 3},
      {"team": "Czech Republic", "position": 4, "points": 1, "played": 3, "won": 0, "draw": 1, "lost": 2, "goal_difference": -3, "goals_for": 2, "goals_against": 5}
    ],
    "B": [
      {"team": "Switzerland", "position": 1, "points": 7, "played": 3, "won": 2, "draw": 1, "lost": 0, "goal_difference": 4, "goals_for": 7, "goals_against": 3},
      {"team": "Canada", "position": 2, "points": 4, "played": 3, "won": 1, "draw": 1, "lost": 1, "goal_difference": 4, "goals_for": 7, "goals_against": 3},
      {"team": "Bosnia and Herzegovina", "position": 3, "points": 4, "played": 3, "won": 1, "draw": 1, "lost": 1, "goal_difference": 0, "goals_for": 5, "goals_against": 5},
      {"team": "Qatar", "position": 4, "points": 1, "played": 3, "won": 0, "draw": 1, "lost": 2, "goal_difference": -8, "goals_for": 2, "goals_against": 10}
    ],
    "C": [
      {"team": "Brazil", "position": 1, "points": 7, "played": 3, "won": 2, "draw": 1, "lost": 0, "goal_difference": 4, "goals_for": 7, "goals_against": 3},
      {"team": "Morocco", "position": 2, "points": 7, "played": 3, "won": 2, "draw": 1, "lost": 0, "goal_difference": 2, "goals_for": 6, "goals_against": 4},
      {"team": "Scotland", "position": 3, "points": 3, "played": 3, "won": 1, "draw": 0, "lost": 2, "goal_difference": -3, "goals_for": 1, "goals_against": 4},
      {"team": "Haiti", "position": 4, "points": 0, "played": 3, "won": 0, "draw": 0, "lost": 3, "goal_difference": -3, "goals_for": 2, "goals_against": 5}
    ],
    "D": [
      {"team": "USA", "position": 1, "points": 6, "played": 3, "won": 2, "draw": 0, "lost": 1, "goal_difference": 3, "goals_for": 6, "goals_against": 3},
      {"team": "Paraguay", "position": 2, "points": 4, "played": 3, "won": 1, "draw": 1, "lost": 1, "goal_difference": 0, "goals_for": 2, "goals_against": 2},
      {"team": "Australia", "position": 3, "points": 4, "played": 3, "won": 1, "draw": 1, "lost": 1, "goal_difference": 0, "goals_for": 2, "goals_against": 2},
      {"team": "Turkey", "position": 4, "points": 3, "played": 3, "won": 1, "draw": 0, "lost": 2, "goal_difference": -3, "goals_for": 3, "goals_against": 6}
    ],
    "E": [
      {"team": "Germany", "position": 1, "points": 6, "played": 3, "won": 2, "draw": 0, "lost": 1, "goal_difference": 5, "goals_for": 9, "goals_against": 4},
      {"team": "Ivory Coast", "position": 2, "points": 6, "played": 3, "won": 2, "draw": 0, "lost": 1, "goal_difference": 1, "goals_for": 3, "goals_against": 2},
      {"team": "Ecuador", "position": 3, "points": 4, "played": 3, "won": 1, "draw": 1, "lost": 1, "goal_difference": 0, "goals_for": 3, "goals_against": 3},
      {"team": "Curacao", "position": 4, "points": 1, "played": 3, "won": 0, "draw": 1, "lost": 2, "goal_difference": -6, "goals_for": 0, "goals_against": 6}
    ],
    "F": [
      {"team": "Netherlands", "position": 1, "points": 7, "played": 3, "won": 2, "draw": 1, "lost": 0, "goal_difference": 5, "goals_for": 12, "goals_against": 7},
      {"team": "Japan", "position": 2, "points": 5, "played": 3, "won": 1, "draw": 2, "lost": 0, "goal_difference": 2, "goals_for": 7, "goals_against": 5},
      {"team": "Sweden", "position": 3, "points": 4, "played": 3, "won": 1, "draw": 1, "lost": 1, "goal_difference": 0, "goals_for": 7, "goals_against": 7},
      {"team": "Tunisia", "position": 4, "points": 1, "played": 3, "won": 0, "draw": 1, "lost": 2, "goal_difference": -7, "goals_for": 2, "goals_against": 9}
    ],
    "G": [
      {"team": "Belgium", "position": 1, "points": 5, "played": 3, "won": 1, "draw": 2, "lost": 0, "goal_difference": 4, "goals_for": 7, "goals_against": 3},
      {"team": "Egypt", "position": 2, "points": 5, "played": 3, "won": 1, "draw": 2, "lost": 0, "goal_difference": 2, "goals_for": 5, "goals_against": 3},
      {"team": "Iran", "position": 3, "points": 3, "played": 3, "won": 0, "draw": 3, "lost": 0, "goal_difference": 0, "goals_for": 4, "goals_against": 4},
      {"team": "New Zealand", "position": 4, "points": 1, "played": 3, "won": 0, "draw": 1, "lost": 2, "goal_difference": -6, "goals_for": 4, "goals_against": 10}
    ],
    "H": [
      {"team": "Spain", "position": 1, "points": 7, "played": 3, "won": 2, "draw": 1, "lost": 0, "goal_difference": 4, "goals_for": 5, "goals_against": 1},
      {"team": "Cape Verde", "position": 2, "points": 5, "played": 3, "won": 1, "draw": 2, "lost": 0, "goal_difference": 1, "goals_for": 3, "goals_against": 2},
      {"team": "Uruguay", "position": 3, "points": 2, "played": 3, "won": 0, "draw": 2, "lost": 1, "goal_difference": -1, "goals_for": 3, "goals_against": 4},
      {"team": "Saudi Arabia", "position": 4, "points": 2, "played": 3, "won": 0, "draw": 2, "lost": 1, "goal_difference": -4, "goals_for": 2, "goals_against": 6}
    ],
    "I": [
      {"team": "France", "position": 1, "points": 9, "played": 3, "won": 3, "draw": 0, "lost": 0, "goal_difference": 6, "goals_for": 9, "goals_against": 3},
      {"team": "Norway", "position": 2, "points": 3, "played": 3, "won": 1, "draw": 0, "lost": 2, "goal_difference": -1, "goals_for": 7, "goals_against": 8},
      {"team": "Senegal", "position": 3, "points": 3, "played": 3, "won": 1, "draw": 0, "lost": 2, "goal_difference": 0, "goals_for": 8, "goals_against": 8},
      {"team": "Iraq", "position": 4, "points": 3, "played": 3, "won": 1, "draw": 0, "lost": 2, "goal_difference": -5, "goals_for": 6, "goals_against": 11}
    ],
    "J": [
      {"team": "Argentina", "position": 1, "points": 7, "played": 3, "won": 2, "draw": 1, "lost": 0, "goal_difference": 4, "goals_for": 8, "goals_against": 4},
      {"team": "Austria", "position": 2, "points": 4, "played": 3, "won": 1, "draw": 1, "lost": 1, "goal_difference": 0, "goals_for": 7, "goals_against": 7},
      {"team": "Algeria", "position": 3, "points": 2, "played": 3, "won": 0, "draw": 2, "lost": 1, "goal_difference": -1, "goals_for": 6, "goals_against": 7},
      {"team": "Jordan", "position": 4, "points": 2, "played": 3, "won": 0, "draw": 2, "lost": 1, "goal_difference": -3, "goals_for": 5, "goals_against": 8}
    ],
    "K": [
      {"team": "Portugal", "position": 1, "points": 7, "played": 3, "won": 2, "draw": 1, "lost": 0, "goal_difference": 5, "goals_for": 6, "goals_against": 1},
      {"team": "Colombia", "position": 2, "points": 7, "played": 3, "won": 2, "draw": 1, "lost": 0, "goal_difference": 2, "goals_for": 4, "goals_against": 2},
      {"team": "RD Congo", "position": 3, "points": 3, "played": 3, "won": 1, "draw": 0, "lost": 2, "goal_difference": 0, "goals_for": 4, "goals_against": 4},
      {"team": "Uzbekistan", "position": 4, "points": 0, "played": 3, "won": 0, "draw": 0, "lost": 3, "goal_difference": -7, "goals_for": 2, "goals_against": 9}
    ],
    "L": [
      {"team": "England", "position": 1, "points": 7, "played": 3, "won": 2, "draw": 1, "lost": 0, "goal_difference": 3, "goals_for": 6, "goals_against": 3},
      {"team": "Croatia", "position": 2, "points": 6, "played": 3, "won": 2, "draw": 0, "lost": 1, "goal_difference": 1, "goals_for": 4, "goals_against": 3},
      {"team": "Ghana", "position": 3, "points": 3, "played": 3, "won": 1, "draw": 0, "lost": 2, "goal_difference": -1, "goals_for": 2, "goals_against": 3},
      {"team": "Panama", "position": 4, "points": 0, "played": 3, "won": 0, "draw": 0, "lost": 3, "goal_difference": -3, "goals_for": 0, "goals_against": 3}
    ]
  },
  "matches": [
    {"date": "2026-06-11T19:00:00Z", "home_team": "Mexico", "away_team": "South Africa", "home_goals": 2, "away_goals": 0, "stage": "group", "group": "A", "status": "FINISHED"},
    {"date": "2026-06-12T02:00:00Z", "home_team": "South Korea", "away_team": "Czech Republic", "home_goals": 2, "away_goals": 1, "stage": "group", "group": "A", "status": "FINISHED"},
    {"date": "2026-06-12T19:00:00Z", "home_team": "Canada", "away_team": "Bosnia and Herzegovina", "home_goals": 1, "away_goals": 1, "stage": "group", "group": "B", "status": "FINISHED"},
    {"date": "2026-06-13T01:00:00Z", "home_team": "USA", "away_team": "Paraguay", "home_goals": 4, "away_goals": 1, "stage": "group", "group": "D", "status": "FINISHED"},
    {"date": "2026-06-13T22:00:00Z", "home_team": "Brazil", "away_team": "Morocco", "home_goals": 1, "away_goals": 1, "stage": "group", "group": "C", "status": "FINISHED"},
    {"date": "2026-06-14T01:00:00Z", "home_team": "Australia", "away_team": "Turkey", "home_goals": 2, "away_goals": 0, "stage": "group", "group": "D", "status": "FINISHED"},
    {"date": "2026-06-14T01:00:00Z", "home_team": "Haiti", "away_team": "Scotland", "home_goals": 0, "away_goals": 1, "stage": "group", "group": "C", "status": "FINISHED"},
    {"date": "2026-06-14T01:00:00Z", "home_team": "Qatar", "away_team": "Switzerland", "home_goals": 1, "away_goals": 1, "stage": "group", "group": "B", "status": "FINISHED"},
    {"date": "2026-06-14T17:00:00Z", "home_team": "Germany", "away_team": "Curacao", "home_goals": 7, "away_goals": 1, "stage": "group", "group": "E", "status": "FINISHED"},
    {"date": "2026-06-14T20:00:00Z", "home_team": "Ivory Coast", "away_team": "Ecuador", "home_goals": 1, "away_goals": 0, "stage": "group", "group": "E", "status": "FINISHED"},
    {"date": "2026-06-14T23:00:00Z", "home_team": "Netherlands", "away_team": "Japan", "home_goals": 2, "away_goals": 2, "stage": "group", "group": "F", "status": "FINISHED"},
    {"date": "2026-06-15T02:00:00Z", "home_team": "Sweden", "away_team": "Tunisia", "home_goals": 5, "away_goals": 1, "stage": "group", "group": "F", "status": "FINISHED"},
    {"date": "2026-06-15T19:00:00Z", "home_team": "Spain", "away_team": "Cape Verde", "home_goals": 0, "away_goals": 0, "stage": "group", "group": "H", "status": "FINISHED"},
    {"date": "2026-06-15T22:00:00Z", "home_team": "Saudi Arabia", "away_team": "Uruguay", "home_goals": 1, "away_goals": 1, "stage": "group", "group": "H", "status": "FINISHED"},
    {"date": "2026-06-16T01:00:00Z", "home_team": "Belgium", "away_team": "Egypt", "home_goals": 1, "away_goals": 1, "stage": "group", "group": "G", "status": "FINISHED"},
    {"date": "2026-06-16T04:00:00Z", "home_team": "Iran", "away_team": "New Zealand", "home_goals": 2, "away_goals": 2, "stage": "group", "group": "G", "status": "FINISHED"},
    {"date": "2026-06-16T19:00:00Z", "home_team": "France", "away_team": "Senegal", "home_goals": 3, "away_goals": 1, "stage": "group", "group": "I", "status": "FINISHED"},
    {"date": "2026-06-16T22:00:00Z", "home_team": "Iraq", "away_team": "Norway", "home_goals": 1, "away_goals": 4, "stage": "group", "group": "I", "status": "FINISHED"},
    {"date": "2026-06-17T01:00:00Z", "home_team": "Argentina", "away_team": "Algeria", "home_goals": 3, "away_goals": 0, "stage": "group", "group": "J", "status": "FINISHED"},
    {"date": "2026-06-17T04:00:00Z", "home_team": "Austria", "away_team": "Jordan", "home_goals": 3, "away_goals": 1, "stage": "group", "group": "J", "status": "FINISHED"},
    {"date": "2026-06-17T19:00:00Z", "home_team": "England", "away_team": "Croatia", "home_goals": 4, "away_goals": 2, "stage": "group", "group": "L", "status": "FINISHED"},
    {"date": "2026-06-17T22:00:00Z", "home_team": "Ghana", "away_team": "Panama", "home_goals": 1, "away_goals": 0, "stage": "group", "group": "L", "status": "FINISHED"},
    {"date": "2026-06-18T01:00:00Z", "home_team": "Portugal", "away_team": "RD Congo", "home_goals": 1, "away_goals": 1, "stage": "group", "group": "K", "status": "FINISHED"},
    {"date": "2026-06-18T04:00:00Z", "home_team": "Uzbekistan", "away_team": "Colombia", "home_goals": 1, "away_goals": 3, "stage": "group", "group": "K", "status": "FINISHED"},
    {"date": "2026-06-29T16:00:00Z", "home_team": "Germany", "away_team": "Paraguay", "home_goals": 1, "away_goals": 1, "stage": "round32", "status": "FINISHED", "match_no": 74},
    {"date": "2026-06-29T20:00:00Z", "home_team": "Netherlands", "away_team": "Morocco", "home_goals": 1, "away_goals": 1, "stage": "round32", "status": "FINISHED", "match_no": 75},
    {"date": "2026-06-29T23:00:00Z", "home_team": "Brazil", "away_team": "Japan", "home_goals": 2, "away_goals": 1, "stage": "round32", "status": "FINISHED", "match_no": 76},
    {"date": "2026-06-30T16:00:00Z", "home_team": "France", "away_team": "Sweden", "stage": "round32", "status": "SCHEDULED", "match_no": 77},
    {"date": "2026-06-30T20:00:00Z", "home_team": "Ivory Coast", "away_team": "Norway", "stage": "round32", "status": "SCHEDULED", "match_no": 78},
    {"date": "2026-06-30T23:00:00Z", "home_team": "Mexico", "away_team": "Ecuador", "stage": "round32", "status": "SCHEDULED", "match_no": 79},
    {"date": "2026-07-01T16:00:00Z", "home_team": "England", "away_team": "RD Congo", "stage": "round32", "status": "SCHEDULED", "match_no": 80},
    {"date": "2026-07-01T20:00:00Z", "home_team": "USA", "away_team": "Bosnia and Herzegovina", "stage": "round32", "status": "SCHEDULED", "match_no": 81},
    {"date": "2026-07-01T23:00:00Z", "home_team": "Belgium", "away_team": "Senegal", "stage": "round32", "status": "SCHEDULED", "match_no": 82},
    {"date": "2026-07-02T16:00:00Z", "home_team": "Portugal", "away_team": "Croatia", "stage": "round32", "status": "SCHEDULED", "match_no": 83},
    {"date": "2026-07-02T20:00:00Z", "home_team": "Spain", "away_team": "Austria", "stage": "round32", "status": "SCHEDULED", "match_no": 84},
    {"date": "2026-07-02T23:00:00Z", "home_team": "Switzerland", "away_team": "Algeria", "stage": "round32", "status": "SCHEDULED", "match_no": 85},
    {"date": "2026-07-03T16:00:00Z", "home_team": "Argentina", "away_team": "Cape Verde", "stage": "round32", "status": "SCHEDULED", "match_no": 86},
    {"date": "2026-07-03T20:00:00Z", "home_team": "Colombia", "away_team": "Ghana", "stage": "round32", "status": "SCHEDULED", "match_no": 87},
    {"date": "2026-07-03T23:00:00Z", "home_team": "Australia", "away_team": "Egypt", "stage": "round32", "status": "SCHEDULED", "match_no": 88},
    {"date": "2026-07-04T17:00:00Z", "home_team": "TBD", "away_team": "TBD", "stage": "round16", "status": "SCHEDULED", "match_no": 89, "note": "W74 vs W77"},
    {"date": "2026-07-04T21:00:00Z", "home_team": "Canada", "away_team": "TBD", "stage": "round16", "status": "SCHEDULED", "match_no": 90, "note": "Canada vs W75"},
    {"date": "2026-07-05T17:00:00Z", "home_team": "TBD", "away_team": "TBD", "stage": "round16", "status": "SCHEDULED", "match_no": 91},
    {"date": "2026-07-05T21:00:00Z", "home_team": "TBD", "away_team": "TBD", "stage": "round16", "status": "SCHEDULED", "match_no": 92},
    {"date": "2026-07-09T20:00:00Z", "home_team": "TBD", "away_team": "TBD", "stage": "quarter", "status": "SCHEDULED", "match_no": 97},
    {"date": "2026-07-10T20:00:00Z", "home_team": "TBD", "away_team": "TBD", "stage": "quarter", "status": "SCHEDULED", "match_no": 98},
    {"date": "2026-07-14T19:00:00Z", "home_team": "TBD", "away_team": "TBD", "stage": "semi", "status": "SCHEDULED", "match_no": 101},
    {"date": "2026-07-15T19:00:00Z", "home_team": "TBD", "away_team": "TBD", "stage": "semi", "status": "SCHEDULED", "match_no": 102},
    {"date": "2026-07-19T19:00:00Z", "home_team": "TBD", "away_team": "TBD", "stage": "final", "status": "SCHEDULED", "match_no": 104}
  ]
}
